{
  "formatVersion": 1,
  "database": {
    "version": 1,
    "identityHash": "649891dcd7ea18688d4af4a8295abc76",
    "entities": [
      {
        "tableName": "wordlist",
        "createSql": "CREATE TABLE IF NOT EXISTS `${TABLE_NAME}` (`_id` INTEGER PRIMARY KEY AUTOINCREMENT NOT NULL, `level` TEXT NOT NULL, `artikel` TEXT, `name` TEXT NOT NULL, `examplename` TEXT NOT NULL, `favourite` INTEGER NOT NULL)",
        "fields": [
          {
            "fieldPath": "mWordId",
            "columnName": "_id",
            "affinity": "INTEGER",
            "notNull": true
          },
          {
            "fieldPath": "mWordLevel",
            "columnName": "level",
            "affinity": "TEXT",
            "notNull": true
          },
          {
            "fieldPath": "mWordArtikel",
            "columnName": "artikel",
            "affinity": "TEXT",
            "notNull": false
          },
          {
            "fieldPath": "mWordName",
            "columnName": "name",
            "affinity": "TEXT",
            "notNull": true
          },
          {
            "fieldPath": "mWordExample",
            "columnName": "examplename",
            "affinity": "TEXT",
            "notNull": true
          },
          {
            "fieldPath": "mWordFavourite",
            "columnName": "favourite",
            "affinity": "INTEGER",
            "notNull": true
          }
        ],
        "primaryKey": {
          "columnNames": [
            "_id"
          ],
          "autoGenerate": true
        },
        "indices": [],
        "foreignKeys": []
      }
    ],
    "setupQueries": [
      "CREATE TABLE IF NOT EXISTS room_master_table (id INTEGER PRIMARY KEY,identity_hash TEXT)",
      "INSERT OR REPLACE INTO room_master_table (id,identity_hash) VALUES(42, \"649891dcd7ea18688d4af4a8295abc76\")"
    ]
  }
}